MANIFEST.in
README.rst
setup.py
collective/__init__.py
collective.fbshare.egg-info/PKG-INFO
collective.fbshare.egg-info/SOURCES.txt
collective.fbshare.egg-info/dependency_links.txt
collective.fbshare.egg-info/entry_points.txt
collective.fbshare.egg-info/namespace_packages.txt
collective.fbshare.egg-info/not-zip-safe
collective.fbshare.egg-info/requires.txt
collective.fbshare.egg-info/top_level.txt
collective/fbshare/__init__.py
collective/fbshare/configure.zcml
collective/fbshare/interfaces.py
collective/fbshare/setuphandlers.py
collective/fbshare/testing.py
collective/fbshare/upgrades.zcml
collective/fbshare/vocabularies.py
collective/fbshare/Extensions/install.py
collective/fbshare/browser/SettingsGraph.png
collective/fbshare/browser/__init__.py
collective/fbshare/browser/configure.zcml
collective/fbshare/browser/controlpanel.py
collective/fbshare/browser/opengraph_meta.pt
collective/fbshare/browser/site_opengraph_meta.pt
collective/fbshare/browser/view.py
collective/fbshare/browser/viewlet.py
collective/fbshare/browser/sc_social_like/__init__.py
collective/fbshare/browser/sc_social_like/configure.zcml
collective/fbshare/browser/sc_social_like/fbplugin.py
collective/fbshare/browser/sc_social_like/metadata.pt
collective/fbshare/locales/collective.fbshare-manual.pot
collective/fbshare/locales/collective.fbshare.pot
collective/fbshare/locales/rebuildPo.sh
collective/fbshare/locales/it/LC_MESSAGES/collective.fbshare.mo
collective/fbshare/locales/it/LC_MESSAGES/collective.fbshare.po
collective/fbshare/profiles/default/browserlayer.xml
collective/fbshare/profiles/default/controlpanel.xml
collective/fbshare/profiles/default/metadata.xml
collective/fbshare/profiles/default/registry.xml
collective/fbshare/profiles/default/rolemap.xml
collective/fbshare/profiles/uninstall/browserlayer.xml
collective/fbshare/profiles/uninstall/controlpanel.xml
collective/fbshare/profiles/uninstall/registry.xml
collective/fbshare/tests/__init__.py
collective/fbshare/tests/base.py
collective/fbshare/tests/plone-icon.png
collective/fbshare/tests/test_view.py
collective/fbshare/tests/test_viewlet.py
docs/HISTORY.rst
docs/INSTALL.txt
docs/LICENSE.GPL
docs/LICENSE.txt