Metadata-Version: 1.0
Name: collective.fbshare
Version: 0.3.1
Summary: Provide some additional Open Graph meta tag in your Plone site, so share items on Facebook will be simpler
Home-page: http://plone.org/products/collective.fbshare
Author: RedTurtle Technology
Author-email: sviluppoplone@redturtle.it
License: GPL
Keywords: plone plonegov opengraph facebook
Platform: UNKNOWN
Classifier: Development Status :: 5 - Production/Stable
Classifier: Framework :: Plone
Classifier: Framework :: Plone :: 3.3
Classifier: Framework :: Plone :: 4.0
Classifier: Framework :: Plone :: 4.1
Classifier: Framework :: Plone :: 4.2
Classifier: Framework :: Plone :: 4.3
Classifier: Programming Language :: Python
